cdndl/__init__.py
cdndl/main.py
cdn_dl-2.4.dist-info/METADATA
cdn_dl-2.4.dist-info/WHEEL
cdn_dl-2.4.dist-info/entry_points.txt
cdn_dl-2.4.dist-info/top_level.txt
cdn_dl-2.4.dist-info/RECORD
