Metadata-Version: 2.1
Name: cdn-dl
Version: 2.4
Summary: 通过cdn 下载文件
Author: nobitaqaq
Author-email: xiaoleigs@gmail.com
Keywords: cdn-dl,cdn 文件下载器
Requires-Python: >=3.8
Requires-Dist: urllib3
Requires-Dist: requests
